[
  {
    "id": 17580036,
    "title_fa": "گوشی موبایل شیائومی مدل Redmi Note 14 4G دو سیم کارت ظرفیت 256 گیگابایت و رم 8 گیگابایت",
    "title_en": "Xiaomi Redmi Note 14 4G Dual SIM Storage 256GB And RAM 8GB Mobile Phone",
    "brand": "",
    "price": 174300000,
    "price_formatted": "174,300,000 ریال",
    "rating": 88.93,
    "rating_count": 5053,
    "url": "https://www.digikala.com/product/dkp-17580036",
    "image": "https://dkstatics-public.digikala.com/digikala-products/c0a7ce006d11c222bce16bd3cdd8d79aeb6689bc_1738134271.jpg?x-oss-process=image/resize,m_lfit,h_300,w_300/quality,q_80",
    "colors": [
      "سبز",
      "آبی",
      "مشکی",
      "بنفش"
    ],
    "specifications": {},
    "is_available": false
  },
  {
    "id": 19347047,
    "title_fa": "گوشی موبایل شیائومی مدل Poco C71 دو سیم کارت ظرفیت 128 گیگابایت و رم 4 گیگابایت",
    "title_en": "Xiaomi Poco C71 Dual SIM Storage 128GB And 4GB RAM Mobile Phone",
    "brand": "",
    "price": 80900000,
    "price_formatted": "80,900,000 ریال",
    "rating": 83.93,
    "rating_count": 1431,
    "url": "https://www.digikala.com/product/dkp-19347047",
    "image": "https://dkstatics-public.digikala.com/digikala-products/935cb213b0d1c0982296c017df69d4df4b8401cb_1759669542.jpg?x-oss-process=image/resize,m_lfit,h_300,w_300/quality,q_80",
    "colors": [
      "مشکی",
      "آبی"
    ],
    "specifications": {},
    "is_available": false
  },
  {
    "id": 19041413,
    "title_fa": "گوشی موبایل شیائومی مدل Redmi A5 دو سیم کارت ظرفیت 128 گیگابایت و رم 4 گیگابایت - نسخه به همراه شارژر",
    "title_en": "Xiaomi Redmi A5 Dual SIM Storage 128GB And 4GB RAM Mobile Phone - With Charger Version",
    "brand": "",
    "price": 80600000,
    "price_formatted": "80,600,000 ریال",
    "rating": 85.17,
    "rating_count": 1276,
    "url": "https://www.digikala.com/product/dkp-19041413",
    "image": "https://dkstatics-public.digikala.com/digikala-products/6c9d6f5d36234b06ba6c2514f3cf169f16f4ce30_1746520092.jpg?x-oss-process=image/resize,m_lfit,h_300,w_300/quality,q_80",
    "colors": [
      "مشکی",
      "طلایی",
      "آبی"
    ],
    "specifications": {},
    "is_available": false
  },
  {
    "id": 16552148,
    "title_fa": " گوشی موبایل سامسونگ مدل Galaxy A06 دو سیم کارت ظرفیت 64 گیگابایت و رم 4 گیگابایت",
    "title_en": " Samsung Galaxy A06 Dual SIM Storage 64GB And RAM 4GB Mobile Phone",
    "brand": "",
    "price": 84819300,
    "price_formatted": "84,819,300 ریال",
    "rating": 86.14,
    "rating_count": 3934,
    "url": "https://www.digikala.com/product/dkp-16552148",
    "image": "https://dkstatics-public.digikala.com/digikala-products/eb60f4f53673db70d9870952cd053626ccfd8b6d_1763240073.jpg?x-oss-process=image/resize,m_lfit,h_300,w_300/quality,q_80",
    "colors": [
      "آبی روشن",
      "طلایی",
      "مشکی",
      "سبز روشن"
    ],
    "specifications": {},
    "is_available": false
  },
  {
    "id": 17464125,
    "title_fa": "گوشی موبایل سامسونگ مدل Galaxy A16 4G دو سیم کارت ظرفیت 128 گیگابایت و رم 4 گیگابایت - ویتنام",
    "title_en": " Samsung Galaxy A16 4G Dual SIM Storage 128GB And 4GB RAM Mobile Phone - Vietnam",
    "brand": "",
    "price": 130480600,
    "price_formatted": "130,480,600 ریال",
    "rating": 89.61,
    "rating_count": 2034,
    "url": "https://www.digikala.com/product/dkp-17464125",
    "image": "https://dkstatics-public.digikala.com/digikala-products/b9036d74149f629611d958331c26541854c3d4f2_1763240650.jpg?x-oss-process=image/resize,m_lfit,h_300,w_300/quality,q_80",
    "colors": [
      "مشکی",
      "خاکستری",
      "سبز روشن",
      "سبز"
    ],
    "specifications": {},
    "is_available": false
  },
  {
    "id": 17464490,
    "title_fa": "گوشی موبایل سامسونگ مدل Galaxy A16 4G دو سیم کارت ظرفیت 128 گیگابایت و رم 6 گیگابایت - ویتنام",
    "title_en": "Samsung Galaxy A16 4G Dual SIM Storage 128GB And 6GB RAM Mobile Phone - Vietnam",
    "brand": "",
    "price": 156900000,
    "price_formatted": "156,900,000 ریال",
    "rating": 90.17,
    "rating_count": 2463,
    "url": "https://www.digikala.com/product/dkp-17464490",
    "image": "https://dkstatics-public.digikala.com/digikala-products/b07e66e28603bd9655bce180fb46d4047412a3fa_1737985896.jpg?x-oss-process=image/resize,m_lfit,h_300,w_300/quality,q_80",
    "colors": [
      "مشکی",
      "خاکستری",
      "سبز روشن"
    ],
    "specifications": {},
    "is_available": false
  },
  {
    "id": 18575915,
    "title_fa": "گوشی موبایل سامسونگ مدل Galaxy A56 دو سیم کارت ظرفیت 256 گیگابایت و رم 8 گیگابایت - ویتنام",
    "title_en": "Samsung Galaxy A56 Dual SIM Storage 256GB And 8GB RAM Mobile Phone - Vietnam",
    "brand": "",
    "price": 377000000,
    "price_formatted": "377,000,000 ریال",
    "rating": 91.08,
    "rating_count": 1265,
    "url": "https://www.digikala.com/product/dkp-18575915",
    "image": "https://dkstatics-public.digikala.com/digikala-products/abb89918836e519343bdad17448cda4adeff4d4e_1746028045.jpg?x-oss-process=image/resize,m_lfit,h_300,w_300/quality,q_80",
    "colors": [
      "زیتونی",
      "مشکی",
      "خاکستری روشن",
      "صورتی"
    ],
    "specifications": {},
    "is_available": false
  },
  {
    "id": 20109389,
    "title_fa": "گوشی موبایل سامسونگ مدل Galaxy A07 دو سیم کارت ظرفیت 64 گیگابایت و رم 4 گیگابایت",
    "title_en": "Samsung Galaxy A07 Dual SIM Storage 64GB And 4GB RAM Mobile Phone",
    "brand": "",
    "price": 91293000,
    "price_formatted": "91,293,000 ریال",
    "rating": 87.05,
    "rating_count": 292,
    "url": "https://www.digikala.com/product/dkp-20109389",
    "image": "https://dkstatics-public.digikala.com/digikala-products/6e193ccbadf1dd14bc3f15df8050006e44c96846_1763385148.jpg?x-oss-process=image/resize,m_lfit,h_300,w_300/quality,q_80",
    "colors": [
      "سبز",
      "مشکی",
      "یاسی"
    ],
    "specifications": {},
    "is_available": false
  },
  {
    "id": 19038990,
    "title_fa": "گوشی موبایل شیائومی مدل Redmi 13x دو سیم کارت ظرفیت 256 گیگابایت و رم 8 گیگابایت",
    "title_en": "Xiaomi Redmi 13x Dual SIM Storage 256GB And 8GB RAM Mobile Phone",
    "brand": "",
    "price": 131951000,
    "price_formatted": "131,951,000 ریال",
    "rating": 85.73,
    "rating_count": 1036,
    "url": "https://www.digikala.com/product/dkp-19038990",
    "image": "https://dkstatics-public.digikala.com/digikala-products/139137be649919f1e1a78d1a28ee371c499a270e_1746519906.jpg?x-oss-process=image/resize,m_lfit,h_300,w_300/quality,q_80",
    "colors": [
      "مشکی",
      "طلایی"
    ],
    "specifications": {},
    "is_available": false
  },
  {
    "id": 17986495,
    "title_fa": "گوشی موبایل اپل مدل iPhone 16 CH دو سیم کارت ظرفیت 128 گیگابایت و رم 8 گیگابایت",
    "title_en": "Apple iPhone 16 CH Dual SIM Storage 128GB And RAM 8GB Mobile Phone",
    "brand": "",
    "price": 1096990000,
    "price_formatted": "1,096,990,000 ریال",
    "rating": 90.22,
    "rating_count": 2319,
    "url": "https://www.digikala.com/product/dkp-17986495",
    "image": "https://dkstatics-public.digikala.com/digikala-products/5af568b4909435c6a215ad5e728e902db234b673_1736597759.jpg?x-oss-process=image/resize,m_lfit,h_300,w_300/quality,q_80",
    "colors": [
      "سفید",
      "مشکی",
      "سبز",
      "آبی",
      "صورتی"
    ],
    "specifications": {},
    "is_available": false
  },
  {
    "id": 20433985,
    "title_fa": "گوشی موبایل شیائومی مدل Poco C85 دو سیم کارت ظرفیت 256 گیگابایت و رم 8 گیگابایت",
    "title_en": "Xiaomi Poco C85 Dual Sim 256GB Storage and 8GB Ram Mobile Phone",
    "brand": "",
    "price": 129900000,
    "price_formatted": "129,900,000 ریال",
    "rating": 90.53,
    "rating_count": 131,
    "url": "https://www.digikala.com/product/dkp-20433985",
    "image": "https://dkstatics-public.digikala.com/digikala-products/2f54eac2ab336094e10e658eef126bbd3b6f38e8_1762948633.jpg?x-oss-process=image/resize,m_lfit,h_300,w_300/quality,q_80",
    "colors": [
      "مشکی",
      "سبز",
      "بنفش"
    ],
    "specifications": {},
    "is_available": false
  },
  {
    "id": 17588414,
    "title_fa": "گوشی موبایل شیائومی مدل Redmi Note 14 Pro 4G دو سیم کارت ظرفیت 256 گیگابایت و رم 8 گیگابایت",
    "title_en": "Xiaomi Redmi Note 14 Pro 4G Dual SIM Storage 256GB And 8GB RAM Mobile Phone",
    "brand": "",
    "price": 234000000,
    "price_formatted": "234,000,000 ریال",
    "rating": 89.35,
    "rating_count": 973,
    "url": "https://www.digikala.com/product/dkp-17588414",
    "image": "https://dkstatics-public.digikala.com/digikala-products/f342fb46a5160efe4698f4582d33e89850447363_1740843590.jpg?x-oss-process=image/resize,m_lfit,h_300,w_300/quality,q_80",
    "colors": [
      "مشکی",
      "آبی",
      "بنفش"
    ],
    "specifications": {},
    "is_available": false
  },
  {
    "id": 19357284,
    "title_fa": "گوشی موبایل شیائومی مدل Redmi A5 دو سیم کارت ظرفیت 64 گیگابایت و رم 3 گیگابایت - نسخه به همراه شارژر",
    "title_en": "Xiaomi Redmi A5 Dual SIM Storage 64GB And 3GB RAM Mobile Phone - With Charger Version",
    "brand": "",
    "price": 69390000,
    "price_formatted": "69,390,000 ریال",
    "rating": 86.79,
    "rating_count": 610,
    "url": "https://www.digikala.com/product/dkp-19357284",
    "image": "https://dkstatics-public.digikala.com/digikala-products/6335b69f80b92cfed983458a1d7cab2497f158bd_1748697740.jpg?x-oss-process=image/resize,m_lfit,h_300,w_300/quality,q_80",
    "colors": [
      "طلایی",
      "آبی",
      "مشکی",
      "سبز"
    ],
    "specifications": {},
    "is_available": false
  },
  {
    "id": 17464492,
    "title_fa": "گوشی موبایل سامسونگ مدل Galaxy A16 4G دو سیم کارت ظرفیت 256 گیگابایت و رم 8 گیگابایت - ویتنام",
    "title_en": "Samsung Galaxy A16 4G Dual SIM Storage 256GB And 8GB RAM Mobile Phone - Vietnam",
    "brand": "",
    "price": 196500000,
    "price_formatted": "196,500,000 ریال",
    "rating": 89.28,
    "rating_count": 1386,
    "url": "https://www.digikala.com/product/dkp-17464492",
    "image": "https://dkstatics-public.digikala.com/digikala-products/8d7dbac0d444c6265cfab886c1f9b7903f403e08_1737986066.jpg?x-oss-process=image/resize,m_lfit,h_300,w_300/quality,q_80",
    "colors": [
      "مشکی",
      "خاکستری",
      "سبز روشن"
    ],
    "specifications": {},
    "is_available": false
  },
  {
    "id": 17986248,
    "title_fa": "گوشی موبایل شیائومی مدل Poco X7 Pro دو سیم کارت ظرفیت 512 گیگابایت و رم 12 گیگابایت - گلوبال",
    "title_en": "Xiaomi Poco X7 Pro Dual SIM Storage 512GB And RAM 12GB Mobile Phone - Global",
    "brand": "",
    "price": 380400000,
    "price_formatted": "380,400,000 ریال",
    "rating": 91.87,
    "rating_count": 1644,
    "url": "https://www.digikala.com/product/dkp-17986248",
    "image": "https://dkstatics-public.digikala.com/digikala-products/6144c3fdde10110e4312420db31e07f42e2cfc3a_1738146333.jpg?x-oss-process=image/resize,m_lfit,h_300,w_300/quality,q_80",
    "colors": [
      "مشکی",
      "سبز",
      "زرد"
    ],
    "specifications": {},
    "is_available": false
  },
  {
    "id": 19222839,
    "title_fa": "گوشی موبایل سامسونگ مدل Galaxy A26 دو سیم کارت ظرفیت 128 گیگابایت و رم 6 گیگابایت - ویتنام - به همراه هدیه 20 گیگ اینترنت همراه اول",
    "title_en": "Samsung Galaxy A26 Dual SIM Storage 128GB And 6GB RAM Mobile Phone - Vietnam - With Gift 20GB Internet Hamrah Aval",
    "brand": "",
    "price": 201990000,
    "price_formatted": "201,990,000 ریال",
    "rating": 86.46,
    "rating_count": 536,
    "url": "https://www.digikala.com/product/dkp-19222839",
    "image": "https://dkstatics-public.digikala.com/digikala-products/1a804bd34fba94b1af0a827977185cca2078042c_1762957273.jpg?x-oss-process=image/resize,m_lfit,h_300,w_300/quality,q_80",
    "colors": [
      "مشکی",
      "صورتی"
    ],
    "specifications": {},
    "is_available": false
  },
  {
    "id": 16736269,
    "title_fa": "گوشی موبایل سامسونگ مدل S24 FE دو سیم کارت ظرفیت 256 گیگابایت و رم 8 گیگابایت - ویتنام",
    "title_en": "Samsung Galaxy S24 FE Dual SIM Storage 256GB And 8GB Mobile Phone - Vietnam",
    "brand": "",
    "price": 540000000,
    "price_formatted": "540,000,000 ریال",
    "rating": 90.44,
    "rating_count": 3483,
    "url": "https://www.digikala.com/product/dkp-16736269",
    "image": "https://dkstatics-public.digikala.com/digikala-products/915fa5f904618d5c06f10fad876e8666a6e5c000_1737474361.jpg?x-oss-process=image/resize,m_lfit,h_300,w_300/quality,q_80",
    "colors": [
      "خاکستری",
      "مشکی",
      "آبی"
    ],
    "specifications": {},
    "is_available": false
  },
  {
    "id": 20110012,
    "title_fa": "گوشی موبایل سامسونگ مدل Galaxy A07 دو سیم کارت ظرفیت 128 گیگابایت و رم 4 گیگابایت ",
    "title_en": "Samsung Galaxy A07 Dual SIM Storage 128GB And 4GB RAM Mobile Phone",
    "brand": "",
    "price": 110000000,
    "price_formatted": "110,000,000 ریال",
    "rating": 86.91,
    "rating_count": 162,
    "url": "https://www.digikala.com/product/dkp-20110012",
    "image": "https://dkstatics-public.digikala.com/digikala-products/69c8ee8dcb6d825fdb6de8a8515b2a45b4fb7a79_1763385430.jpg?x-oss-process=image/resize,m_lfit,h_300,w_300/quality,q_80",
    "colors": [
      "مشکی",
      "سبز",
      "یاسی"
    ],
    "specifications": {},
    "is_available": false
  },
  {
    "id": 19357767,
    "title_fa": "گوشی موبایل شیائومی مدل Poco C71 دو سیم کارت ظرفیت 64 گیگابایت و رم 3 گیگابایت",
    "title_en": "Xiaomi Poco C71 Dual SIM Storage 64GB And 3GB RAM Mobile Phone",
    "brand": "",
    "price": 69990000,
    "price_formatted": "69,990,000 ریال",
    "rating": 83.48,
    "rating_count": 471,
    "url": "https://www.digikala.com/product/dkp-19357767",
    "image": "https://dkstatics-public.digikala.com/digikala-products/1c2e7d20ad20a75c64926467270d3b01b301d3db_1748425940.jpg?x-oss-process=image/resize,m_lfit,h_300,w_300/quality,q_80",
    "colors": [
      "آبی",
      "مشکی",
      "طلایی"
    ],
    "specifications": {},
    "is_available": false
  },
  {
    "id": 19222844,
    "title_fa": "گوشی موبایل سامسونگ مدل Galaxy A26 دو سیم کارت ظرفیت 256 گیگابایت و رم 8 گیگابایت - ویتنام",
    "title_en": "Samsung Galaxy A26 Dual SIM Storage 256GB And 8GB RAM Mobile Phone - Vietnam",
    "brand": "",
    "price": 254200000,
    "price_formatted": "254,200,000 ریال",
    "rating": 88.71,
    "rating_count": 535,
    "url": "https://www.digikala.com/product/dkp-19222844",
    "image": "https://dkstatics-public.digikala.com/digikala-products/b937b9bf43cccf4ca4cb7f9d1c2d4fc980892cc0_1747574873.jpg?x-oss-process=image/resize,m_lfit,h_300,w_300/quality,q_80",
    "colors": [
      "مشکی",
      "صورتی",
      "سفید"
    ],
    "specifications": {},
    "is_available": false
  }
]